compass/ConditionTransformer.py
compass/ModelTransfuser.py
compass/MultiObsSampler.py
compass/SDE.py
compass/Sampler.py
compass/ScoreBasedInferenceModel.py
compass/Trainer.py
compass/__init__.py
bayes_compass-1.0.3.dist-info/METADATA
bayes_compass-1.0.3.dist-info/WHEEL
bayes_compass-1.0.3.dist-info/licenses/COPYING
bayes_compass-1.0.3.dist-info/RECORD
