Metadata-Version: 2.4
Name: bayes-compass
Version: 1.0.3
Summary: COMPASS: A Python package for bayesian model comparison in a simulation based setting
Project-URL: Homepage, https://github.com/bGuenes/COMPASS
Project-URL: Issues, https://github.com/bGuenes/COMPASS/issues
Author-email: Berkay Günes <b.guenes@stud.uni-heidelberg.de>
License-Expression: GPL-3.0
License-File: COPYING
Classifier: Operating System :: OS Independent
Classifier: Programming Language :: Python :: 3
Requires-Python: >=3.8
Requires-Dist: matplotlib
Requires-Dist: numpy
Requires-Dist: schedulefree
Requires-Dist: scipy
Requires-Dist: seaborn
Requires-Dist: torch
Requires-Dist: tqdm
